{"about.md":"DLbD6Bme","documents-index.md":"BoEHuiji","index.md":"DHIDCUTn","notion_babel.md":"DbeJv7mT","notion_basic _ extra.md":"DQReOfbY","notion_c__.md":"DSMm4uGw","notion_commonjs和es module.md":"BEFPr4ji","notion_css.md":"CPQuFAT9","notion_data为什么是函数问题.md":"DFgBgX0b","notion_dpr和自适应布局.md":"_AkLTx2d","notion_eslint.md":"BO5MuIdM","notion_git.md":"CbQm8A-6","notion_html.md":"n8RmuD2S","notion_index.md":"ZnZB4-a2","notion_indexdb _ websql.md":"D9eioQgb","notion_javascript.md":"CfVw_3QR","notion_let_ var.md":"BX55QM38","notion_linux常用命令.md":"B-DOUOXo","notion_loader.md":"ZaxCfU5U","notion_micro-app.md":"C4aLvM4X","notion_node.md":"BHiMCkDz","notion_notion持续部署github.md":"Dmq-6Q7_","notion_npm _ yarn _ pnpm.md":"2Wey93zx","notion_performance.md":"B2ZQsP1_","notion_prettier.md":"CoFrcHiH","notion_python教程.md":"BZCyIr1P","notion_react.md":"CvypgZL_","notion_ref原理.md":"D8R9dsPB","notion_rollup.md":"BQ8yviEF","notion_socket.md":"C9jWpRtq","notion_tapable.md":"ZJXhZO2n","notion_tcp.md":"BhEgEN_-","notion_this指向、super关键字.md":"DVl9BFrR","notion_tsconfig.md":"D694tX9s","notion_typescript.md":"CtKq8eGt","notion_vite.md":"CRBtSxZ_","notion_vue router.md":"DQAKLeLr","notion_vue.md":"9btJO5lQ","notion_vue2-diff.md":"I2KJswEM","notion_vue3-diff.md":"C07i1wq6","notion_vuex中在mutation中使用异步.md":"Br7QYTJe","notion_web api.md":"Df0Yse2T","notion_web component.md":"BZvDg1ls","notion_webpack.md":"C2KX4GVB","notion_webrtc.md":"BzAZSP51","notion_web前端监控.md":"Dg5VmNwT","notion_web性能.md":"DBVxS1qY","notion_worker.md":"nRDPpH4I","notion_与vue不同点.md":"BDpCp1KQ","notion_作用域和作用域链.md":"LoIhaoNa","notion_前端面试.md":"C29yiD0x","notion_原型和原型链.md":"CipULjro","notion_垃圾回收机制.md":"DymgyZCl","notion_好看的滚动条样式.md":"B2SEDBHS","notion_对象转为可迭代对象.md":"XCx47QP4","notion_工程化_模块化.md":"Bm4Vhou8","notion_常用钩子.md":"u0wzU6D2","notion_开发注意事项.md":"DneORazb","notion_接口问题.md":"CwJmeIni","notion_父组件渲染子组件内容.md":"BnEEmKyu","notion_简单请求_预检请求.md":"4XP3OxE7","notion_类型转换（toprimitive）.md":"5viWhNk3","notion_组件：table移动端表格.md":"CM37JQcl","notion_组件：虚拟列表.md":"1cO-eQyg","notion_缓存.md":"E1OdwzAY","notion_脚手架搭建.md":"CrcDG26f","notion_表格组件自动高度设置.md":"CORLrLd2","notion_计算机网络.md":"raR7X_JC","notion_设计模式.md":"Chfng9rU","notion_迭代器、生成器.md":"DDI7X1zb","notion_问题记录.md":"CWM6R5Yz","notion_阅读记录.md":"DdBudKFb","records_index.md":"Wyh6Zlta","records_vitepress.md":"CEhFtXNZ","tools_index.md":"B1D9Hkmn"}
